testing/__init__.py
testing/elasticsearch.py
testing.elasticsearch-0.3.0.dist-info/DESCRIPTION.rst
testing.elasticsearch-0.3.0.dist-info/METADATA
testing.elasticsearch-0.3.0.dist-info/RECORD
testing.elasticsearch-0.3.0.dist-info/WHEEL
testing.elasticsearch-0.3.0.dist-info/metadata.json
testing.elasticsearch-0.3.0.dist-info/top_level.txt
