Metadata-Version: 2.0
Name: testing.elasticsearch
Version: 0.3.0
Summary: Automatically sets up an elasticsearch instance in a temporary directory, and destroys it after testing
Home-page: https://github.com/jong/testing.elasticsearch
Author: Jon Gartman
Author-email: jongartman@gmail.com
License: MIT
Keywords: testing,elasticsearch
Platform: UNKNOWN
Classifier: Programming Language :: Python
Classifier: Development Status :: 3 - Alpha
Classifier: Intended Audience :: Developers
Classifier: License :: OSI Approved :: MIT License
Classifier: Natural Language :: English
Classifier: Topic :: Software Development :: Libraries :: Python Modules
Requires-Dist: requests (>=2.6.0)
